Chaturanga-0.1.3.dist-info/METADATA
Chaturanga-0.1.3.dist-info/RECORD
Chaturanga-0.1.3.dist-info/WHEEL
Chaturanga-0.1.3.dist-info/top_level.txt
chaturanga/__init__.py
chaturanga/bot.py
chaturanga/check.py
chaturanga/chessboard.py
chaturanga/moves.py
chaturanga/notation.py
chaturanga/update.py
