Metadata-Version: 2.1
Name: Chaturanga
Version: 0.1.3
Summary: Chess API for python
Home-page: https://github.com/Cheran-Senthil/Chaturanga
Author: Cheran
Author-email: UNKNOWN
License: MIT
Platform: UNKNOWN
Requires-Dist: six
Requires-Dist: termcolor
